fastoranalysis/__init__.py
fastoranalysis/factor_analysis.py
tests/__init__.py
tests/test_factor_analysis.py
fastoranalysis-0.1.0.dist-info/LICENSE
fastoranalysis-0.1.0.dist-info/METADATA
fastoranalysis-0.1.0.dist-info/WHEEL
fastoranalysis-0.1.0.dist-info/top_level.txt
fastoranalysis-0.1.0.dist-info/RECORD
