Metadata-Version: 2.1
Name: fastoranalysis
Version: 0.1.0
Summary: A performant factor analysis package for python
Home-page: https://github.com/davidq9199/fastoranalyzer
Author: davidq9199
Classifier: Programming Language :: Python :: 3
Classifier: License :: OSI Approved :: MIT License
Classifier: Operating System :: OS Independent
Requires-Python: >=3.6
License-File: LICENSE
Requires-Dist: numpy
Requires-Dist: scipy
Requires-Dist: pytest
